{"version":1,"resource":"vscode-remote://wsl%2Bubuntu/home/malek/proyectoU/carrito.html","entries":[{"id":"6JSQ.html","source":"textFileCreate.source","timestamp":1714432952792},{"id":"v6RV.html","timestamp":1714441158352},{"id":"ybzC.html","timestamp":1714441202302},{"id":"iWfE.html","timestamp":1714441274572},{"id":"0v0D.html","timestamp":1714441410142},{"id":"XTMf.html","source":"undoRedo.source","timestamp":1714441433522},{"id":"QNXY.html","timestamp":1714442048742},{"id":"jyvT.html","timestamp":1714443147862},{"id":"jpbP.html","timestamp":1714443224742}]}